{"pAPSDATE":"DefaultBuchungsdatum","pTEMPORDER":"Vorl. gebucht Intra-Date-Order","pIADATEBEFISS":"Zins-Zuschreibung Start-Datum","pAPSINITPREMDISC":"Anfangsagio und Disagio pflegen","pCFLWCOMP":"Cashflow-Zusammensetzung","pCFLWCOMPIK":"Cashflow-Zusammensetzung (IK)","pAPSIFRS9CL":"KA Wertberichtigung","pAPSFULLNOMAMO":"Vollständige Nominal-Amortisierung","pACCMETH":"Buchungs-Meth.","pACCMETHNAME":"Buchungsmethode Name","pAPSISSFIFO":"FIFO Emissionstag","pAPSDISTRIB":"Stück-Zinsen auf FRAs","pAPSHDGDISDECR":"Hedge Auflösung bei Verminderungen","pAPSDEFAULTAIIA":"Notl. WP Stückzinsen und Zinszuschreibung","pDEFPLPROFILEIK":"Aufgesch. Gewinn/Verlust Profil (IK)","pDEFPLPROFILE":"Aufgesch. Gewinn/Verlust Profil","pUSEINTTRADECOMP":"Interner Handel Zusammensetz. verw.","pAMORTMKTDISC":"Markt-Disagio für EOP erhöhen","pDGLAMORTISATION":"Aufgeschobener Gewinn/Verlust Amortisation","pAPSQQTAGGING":"Q\u0026\u0026Q Kennzeichnung","pAPSMATCONVCLAUSE":"Fälligkeits-Anpassung für Rückl. f. KA verw.","pAPSMATCONVCLA":"Fälligkeits-Anpassung für Rückl. f. KA","pAPSELIGELIM":"Berechtigt für Eliminierungs-Buchung","pAPSITAGLD":"Italienisches GLD","pCAPRETWITHQUANT":"Kapitalertrag mit Quantität","pAGIODISAFROMISS":"Agio/Disagio vom Emissionsdatum","pAPSDEFLPROT":"Amortisation Deflations-Schutz","pCAPRETWITHOUTQUANT":"Kapitalertrag ohne Quantität","pMATCHTYPEAVGLOTS":"Abgleichs-Art für Durchschnitts-Lots","pAPSINTAPRATPAR":"Zins-Zuschreibung wenn zum Nennw. gekauft","pAPSDIVEXPCRULE":"Dividende Befreiung DW Regel","pAPSIMR":"IMR Amortisierungsmethode","pAPSINTAPRDAYS":"Zinszuschreibungs-Tage Berechnung","pAPSBGHTACRINT":"Gekauften Stückzins beibehalten","pAPSCLADISREDEMP":"Rückl. f. KA Auflösung bei Rückzahlung","pAPSIAAFTNOTEXERC":"Zinszuschreibung, wenn Put/Call-Option nicht ausgeübt","pAGIODISADESPITEMAT":"Agio/Disagio trotz Fälligkeit","pAPSFAIRVALFLOOR":"Fair-Value Floor","pUSEPRICEQUALITY":"Preis-Qualität verwenden","pAPSUNSPECPROCPRLCUR":"Gewinn/Verlust Währ. unspezifizierte Erlöse","pAPSUNSPECPROCEOPADJ":"EOP-Anpassung, unspezifizierte Erlöse","pAPSNAICSVOLACOM":"SVO Rating für NAIC Saldo","pTAXLOTMATCH":"NAIC Tax-Lot Ertrag","pICFPROFREF":"Referenz zum IKG-Profil","pAPSCLACFLW":"Angenommenen Kontrakt-Cashflow für RKA verw.","pBOOKEDCOSTSREF":"Gebuchte Kosten für Kapitalausschüttungen","pCOSTCLSGRPIK":"Kostenklassengruppe (IK)","pCOSTCLSGRP":"Kostenklassengruppe","pCBAPROFILE":"Kosten-Basis Anpassungs-Profil","pCBAPROFILEIK":"Kostenbasis Anpassungsprofil (IK)","pAPSPRLREDEMP":"Gewinn/Verlust Abgleich für Tilgungen","pALTINVPROCEEDS":"Alternative Investment-Erlöse","pDEMINIDEF":"De-minimis-Definition","pDEMINIDEFIK":"De-minimis-Definition (IK)","pAPSTAXLOTPRLAGR":"G/V Ber. für manuellen Abgleich DW","pAPSTAXLOTPRL":"Zusätzliche YtD Tax Lot-Felder","pAPSINTAPRAIEXCL":"Zinszuschreibung, gehandelter AI-Betrag ausgeschlossen","pAPSIMPAIRDISTR":"Impairments Verteilung","pAPSTAXNET":"Tax-Netting","pAPSSUPDEFLAMORT":"Verfälschende Amortisation unterdrücken","pAPSINTAPRBASIS":"Zins-Zuschreibungs-Basis","pAPSCOURATE":"Kupon-Prognose","pMATADJSPL":"Abschreib. oder Wertzuwachs","pAPSHDGADJ":"Hedge-Anpassungs-Buchung","pIRRBUYDISTRIB":"Relative Neuzuweisung Verteilung","pACCRINTSMTH":"Zins-Glättung","pTAXMARKETVAL":"Steuer Marktwert","pAGIODISACOST":"Agio/Disagio inkl./exkl. Aufwand","pFAMCONTRACTTYPE":"Kontraktart","pAGIODISAPMTDATE":"Agio/Disagio-Tage Berechnung","pDRDANDQD":"Dividende Erhaltener Abschlag Zulässige Dividende","pDYNPRLSELDEFIK":"Dynamische Gewinn/Verlust-Auswahl (IK)","pDYNPRLSELDEF":"Dynamische Gewinn/Verlust-Auswahl","pAPSDEFPL":"Gewinn/Verlust Aufschub","pAPSCURADJPC":"Whrg.-Anp. DW für Bankkonto","pIMLBKTIK":"XpressInstrument Unterkontrakt Bucket (IK)","pIMLBKT":"XpressInstrument Unterkontrakt Bucket","pAPSVIRELOT":"Transfer in Tax Lot","pCHOICEDIVTAX":"Gratisaktie Dividende","pFRANKCRED45DAY":"Franking Credit 45 Tage-Regel","pPURACCHISCOST":"P-GAAP Kostenbasis","pAPSIMPAIR":"Impairments","pAPSVARYLDADJ":"Variable Rendite-Anpassung","pAPSEQUALISATION":"Ausgleich","pTAXBKTDEFIK":"Steuer-Bucket (IK)","pTAXBKTDEF":"Steuer-Bucket","pAPSALCLASS":"Aktiva- und Passiva-Klassifikation","pAPSHDGAMRT":"Hedge-Amortisation","pAPSMATCONV":"Fälligkeit Anpassung am","pACCOMPIK":"Zus.-Setz. fortg. Ansch.-Kosten (IK)","pACCOMP":"Zus.-Setz. fortg. Ansch.-Kosten","pINTRADAYFIFO":"Intra-Day FIFO","pAPSTRUEUP":"Zinszuschreibung abstimmen","pAPSGENADJ":"Tax Lot kombinierte Anpassung","pAPSSUPFLDS":"Felder für systemeigene Geschäfte unterdrücken","pAPSBILMOG":"BilMoG Whrg.-Anp.","pDILUTEPERTAXLOT":"Wert-Minderungs-Methode","pEOXMARGIN":"EOX und Margin","pAPSSEPPRL":"Gewinn/Verlust-Trennung","pAPSPRLTRS":"Gewinn/Verlust-Kategorisierung bei TRSs","pAPSPRLLENDING":"Gewinn/Verlust-Abgleich für Leihen","pAGIODISASMTH":"Agio/Disagio-Glättung","pAPSEITFPMT":"Buchwert von Kupons und Tilgungen","pAPSAOCIAMORT":"AOCI Amortisation","pAPSDIRVALADJ":"Interne Besicherungs-Anpassungen","pAPSOIDINTAPRBASIS":"OID Zins-Zuschreibung Basis","pCAPREDCURPL":"Kapitalereignis, Whrg. G/V","pRIGHTSVAL":"Bezugsr.-Wert","pFREECOM":"Freikommentar","pRESFORLOSS":"Verlustrückstellung Anpassung","pSORT":"Sort.","pDISTPMT":"Swap-Zahlungen","pMATADJ":"Zinszuschreibung","pAPSREGAGIO":"Agio/Disagio-Anpassung","pAPSPRLDEV":"Gewinn/Verlust Methode für Derivate","pAPSSORT":"Gewinn/Verlust Sortierung","pAPRPRLRES":"Gewinn/Verlust Restwert","pAPSREGMETHOD":"EOY-Anpassungs-Methode","pAPSPRL":"Gewinn/Verlust-Methode","pAPSLIM":"Short-Check","pAPSCOST":"Buchung von Kosten","pEOPADJPRIN":"EOP Abschreib.-Methode","pADJINTREV":"Zins-Auflösungs-Methode","pAPSIXPRL":"Index G/V","pACCRINTDAYS":"Stück-ZinstagBerechnung","pAPSMATCHINT":"FIFO Umbuchung interne Handelsgeschäfte","pAPSEOXPARDISS":"Tax Lot-bas. EOX Bestands-Auflösung","pAPSFIFOREG":"FIFO-Anpassung","pZWGAKGADJ":"Anpassung steuerpflichtige Einkommens-Komponente","pAPSINTAPRCOUPDAYCOUNTCONV":"Zinszuschr. täglicher Kupon Tageszähl-Konvention","pAPSOIDMATCONV":"OID Fälligkeit Anpassung am","pAPSIADAILYCOUCALC":"Zinszuschr. täglicher Kupon Berechnungsverfahren","pAPSRECOVERYPRICE":"Rückerstattungs-Kurse für ZA-Berechnungen verw."}